pycares/_version.py
pycares/errno.py
pycares/py.typed
pycares/_cares.abi3.so
pycares/__main__.py
pycares/utils.py
pycares/__init__.py
pycares-4.7.0.dist-info/top_level.txt
pycares-4.7.0.dist-info/METADATA
pycares-4.7.0.dist-info/RECORD
pycares-4.7.0.dist-info/WHEEL
pycares-4.7.0.dist-info/licenses/LICENSE
